bellerophon/__init__.py
bellerophon/cli.py
bellerophon-1.0.dist-info/LICENSE
bellerophon-1.0.dist-info/METADATA
bellerophon-1.0.dist-info/WHEEL
bellerophon-1.0.dist-info/entry_points.txt
bellerophon-1.0.dist-info/top_level.txt
bellerophon-1.0.dist-info/RECORD
